hwsoftmcp_weibots/__init__.py
hwsoftmcp_weibots/main.py
hwsoftmcp_weibots-0.0.1.dist-info/METADATA
hwsoftmcp_weibots-0.0.1.dist-info/WHEEL
hwsoftmcp_weibots-0.0.1.dist-info/entry_points.txt
hwsoftmcp_weibots-0.0.1.dist-info/top_level.txt
hwsoftmcp_weibots-0.0.1.dist-info/RECORD
